{"chunk":2,"numChunks":3,"fileHash":"OvwPQrd56mtX/83GlIUJS1gy4SAAnkLV+ra4uFq4H5U=","filePath":"frontend/src/Student/components/FileUploadInput.js","content":"import React, { useState } from 'react'\nfunction FileUploadInput (props) {\n  const [file, setFile] = useState(null)\n  const dropzoneClasses = 'form-control d-flex align-items-center justify-content-center'\n  const name = props.name || 'path'\n  async function onDrop (acceptedFiles) {\n    // Only 1 submission at a time. Grab the first file\n    const file = acceptedFiles[0]\n    switch (file.type) {\n      // application/pdf only for Other Media submission\n      case 'application/pdf':\n        const pdfData = await props.handlePDFUpload(file)\n        setFile(file)\n        props.setFieldValue(name, pdfData.path)\n        break\n      case 'image/jpeg':\n        const imageData = await props.handleImageUpload(file)\n        setFile(file)\n        props.setFieldValue(name, imageData.path)\n        break\n      default:\n        console.error(`Unknown File Type: ${file.type}`)\n    }\n  }"}