{"chunk":4,"numChunks":11,"fileHash":"bVgcirSbZtc05aSdijvkfgnA39tQgHOLY8GCqKrLTt4=","filePath":"backend/test/resolvers/showQuery.js","content":"/* eslint-disable no-unused-expressions */\ndescribe('Show Queries', function () {\n  describe('Show query', function () {\n    it('Finds a show given the id', function (done) {\n      fakeShow().then((s) => {\n        show('', { id: s.id }, { auth: { type: 'ADMIN' } })\n          .then((result) => {\n            expect(result.id).to.equal(s.id)\n            expect(result.entryCap).to.equal(s.entryCap)\n            done()\n          })\n      })\n    })\n  })"}