{"chunk":0,"numChunks":3,"fileHash":"pnmzYVtQERHgurXDNl15MU+kRdJsI1Oq2bdlmcLDUM0=","filePath":"frontend/src/Judge/actions.js","content":"import { push } from 'connected-react-router'\nimport SubmissionQuery from './queries/submission.graphql'\nimport SubmissionsQuery from './queries/submissions.graphql'\nimport { displayError } from '../shared/actions'\nimport ShowVotes from './queries/showVotes.graphql'\nimport GetVote from './queries/entryVote.graphql'\nimport PortfolioPeriodRatings from './queries/portfolioPeriodRatings.graphql'\nimport GetPortfolioRating from './queries/portfolioRating.graphql'\nimport PortfolioQuery from './queries/portfolio.graphql'\nimport PortfoliosQuery from './queries/portfolios.graphql'\nexport const FETCH_SUBMISSION = 'FETCH_SUBMISSION'\nexport const FETCH_SUBMISSIONS = 'FETCH_SUBMISSIONS'\nexport const FETCH_VOTES = 'FETCH_VOTES'\nexport const FETCH_VOTE = 'FETCH_VOTE'\nexport const WILL_FETCH_VOTES = 'WILL_FETCH_VOTES'\nexport const WILL_FETCH_SUBMISSIONS = 'WILL_FETCH_SUBMISSIONS'\nexport const FETCH_PORTFOLIO = 'FETCH_PORTFOLIO'\nexport const FETCH_PORTFOLIOS = 'FETCH_PORTFOLIOS'\nexport const FETCH_PORTFOLIO_RATINGS = 'FETCH_PORTFOLIO_RATINGS'\nexport const FETCH_PORTFOLIO_RATING = 'FETCH_PORTFOLIO_RATING'\nexport const WILL_FETCH_PORTFOLIO_RATINGS = 'WILL_FETCH_PORTFOLIO_RATINGS'\nexport const WILL_FETCH_PORTFOLIOS = 'WILL_FETCH_PORTFOLIOS'\nexport const fetchSubmission = submissionId => (dispatch, getState, client) => {\n  return client\n    .query({\n      query: SubmissionQuery,\n      variables: {\n        id: submissionId\n      }\n    })\n    .then(({ data: { submission } }) =>\n      dispatch({ type: FETCH_SUBMISSION, payload: submission })\n    )\n    .catch(err => dispatch(displayError(err.message)))\n}"}