{"chunk":23,"numChunks":25,"fileHash":"VId2jvAlzGPcQWc/noMCwiN/07xgsdtgqYktj7bczBg=","filePath":"backend/db/seeds/20211026060000-seed-portfolio.js","content":"import moment from 'moment'\nexport function up (queryInterface, Sequelize) {\n    return Promise.all([\n    .then(ids => {\n      return queryInterface.bulkInsert('entries', [\n        // make user 7 add the fish and the tree to their first portfolio\n        {\n          id: fishEntryId,\n          portfolioId: portfolioId1 ,\n          studentUsername: 'user7',\n          entryType: 1,\n          entryId: fishImageId,\n          title: 'Betta In Bloom',\n          comment: '',\n          moreCopies: 1,\n          forSale: 1,\n          yearLevel: 'five',\n          academicProgram: 'Ceramics',\n          createdAt: now.format('YYYY-MM-DD HH:mm:ss'),\n          updatedAt: now.format('YYYY-MM-DD HH:mm:ss')\n        },\n        {\n          id: treeEntryId,\n          portfolioId: portfolioId1 ,\n          studentUsername: 'user7',\n          entryType: 1,\n          entryId: treeImageId,\n          title: 'Tree in the Field',\n          comment: '',\n          moreCopies: 1,\n          forSale: 0,\n          yearLevel: 'five',\n          academicProgram: 'Ceramics',\n          createdAt: now.format('YYYY-MM-DD HH:mm:ss'),\n          updatedAt: now.format('YYYY-MM-DD HH:mm:ss')\n        },\n        // make user 6 add the book to their first portfolio\n        {\n          id: bookEntryId,\n          portfolioId: portfolioId2 ,\n          studentUsername: 'user6',\n          entryType: 1,\n          entryId: bookImageId,\n          title: 'Light Reading',\n          comment: '',\n          moreCopies: 1,\n          forSale: 1,\n          yearLevel: 'four',\n          academicProgram: 'Software Engineering',\n          createdAt: now.format('YYYY-MM-DD HH:mm:ss'),\n          updatedAt: now.format('YYYY-MM-DD HH:mm:ss')\n        },\n"}