{"chunk":1,"numChunks":2,"fileHash":"+K+mY1FdrLt1nTjYcBjin5D27cIPJHeLpFooRzLjm1c=","filePath":"frontend/src/shared/reducers.js","content":"import { combineReducers } from 'redux'\nconst auth = (state = {}, action) => {\n  switch (action.type) {\n    case actions.LOGIN_USER:\n      if (!action.payload || !action.payload.token || !action.payload.user) {\n        return state\n      }\n      return {\n        ...state,\n        token: action.payload.token,\n        user: action.payload.user\n      }\n    case actions.LOGOUT_USER:\n      return {}\n    case actions.SWITCH_TO_JUDGE:\n      return {\n        ...state,\n        performingRole: 'JUDGE'\n      }\n    case actions.SWITCH_TO_ADMIN:\n      return {\n        ...state,\n        performingRole: 'ADMIN'\n      }\n    case actions.GET_DOWNLOAD_TOKEN:\n      if (!action.payload) {\n        return state\n      }\n      return {\n        ...state,\n        downloadToken: action.payload\n      }\n    case actions.SET_USER_HOMETOWN:\n      if (state.user.hometown) {\n        return state;\n      }\n      return {\n        ...state,\n        user: {\n          ...state.user,\n          hometown: action.payload\n        }\n      }\n    case actions.SET_USER_DISPLAY_NAME:\n      if (state.user.displayName) {\n        return state;\n      }\n      return {\n        ...state,\n        user: {\n          ...state.user,\n          displayName: action.payload\n        }\n      }\n    default:\n      return state\n  }\n}\n// 'errors' is a list of strings"}